combox/__init__.py
combox/_version.py
combox/cbox.py
combox/config.py
combox/crypto.py
combox/events.py
combox/file.py
combox/gui.py
combox/log.py
combox/silo.py
combox-0.2.3.dist-info/DESCRIPTION.rst
combox-0.2.3.dist-info/METADATA
combox-0.2.3.dist-info/RECORD
combox-0.2.3.dist-info/WHEEL
combox-0.2.3.dist-info/entry_points.txt
combox-0.2.3.dist-info/metadata.json
combox-0.2.3.dist-info/top_level.txt
