Metadata-Version: 2.0
Name: combox
Version: 0.2.3
Summary: Encrypts files and scatters them across storage provided by Google Drive and Dropbox.
Home-page: https://ricketyspace.net/combox/
Author: combox contributors
Author-email: sravik@bgsu.edu
License: GNU General Public License version 3 or later
Download-URL: https://git.ricketyspace.net/combox
Platform: GNU/Linux
Platform: OS X
Classifier: Development Status :: 3 - Alpha
Classifier: Environment :: Console
Classifier: Environment :: MacOS X
Classifier: Intended Audience :: End Users/Desktop
Classifier: License :: DFSG approved
Classifier: License :: OSI Approved
Classifier: License :: OSI Approved :: GNU General Public License v3 or later (GPLv3+)
Classifier: Operating System :: MacOS :: MacOS X
Classifier: Operating System :: POSIX :: Linux
Classifier: Programming Language :: Python :: 2.7
Classifier: Programming Language :: Python :: 2 :: Only
Classifier: Topic :: System :: Archiving :: Backup
Classifier: Topic :: Utilities
Requires-Dist: PyYAML
Requires-Dist: pickledb
Requires-Dist: pycrypto
Requires-Dist: simplejson
Requires-Dist: watchdog
